itk_clesperanto-0.2.2.data/data/lib/libCLIc.a
itk_clesperanto-0.2.2.data/data/lib/cmake/CLIc/CLIcTargets.cmake
itk_clesperanto-0.2.2.data/data/lib/cmake/CLIc/CLIcTargets-release.cmake
itk_clesperanto-0.2.2.data/data/lib/cmake/CLIc/CLIcConfig.cmake
itk_clesperanto-0.2.2.data/data/lib/cmake/CLIc/CLIcConfigVersion.cmake
itk_clesperanto-0.2.2.data/data/include/CLIc/cleObject.hpp
itk_clesperanto-0.2.2.data/data/include/CLIc/cleScalar.hpp
itk_clesperanto-0.2.2.data/data/include/CLIc/cleKernel.hpp
itk_clesperanto-0.2.2.data/data/include/CLIc/utils.hpp
itk_clesperanto-0.2.2.data/data/include/CLIc/cleKernelList.hpp
itk_clesperanto-0.2.2.data/data/include/CLIc/cleLightObject.hpp
itk_clesperanto-0.2.2.data/data/include/CLIc/clic.hpp
itk_clesperanto-0.2.2.data/data/include/CLIc/cleGPU.hpp
itk_clesperanto-0.2.2.data/data/include/CLIc/clesperanto.hpp
itk_clesperanto-0.2.2.data/data/include/CLIc/CL/cl_icd.h
itk_clesperanto-0.2.2.data/data/include/CLIc/CL/cl_dx9_media_sharing_intel.h
itk_clesperanto-0.2.2.data/data/include/CLIc/CL/cl_ext.h
itk_clesperanto-0.2.2.data/data/include/CLIc/CL/cl_d3d10.h
itk_clesperanto-0.2.2.data/data/include/CLIc/CL/opencl.h
itk_clesperanto-0.2.2.data/data/include/CLIc/CL/cl_ext_intel.h
itk_clesperanto-0.2.2.data/data/include/CLIc/CL/cl_gl_ext.h
itk_clesperanto-0.2.2.data/data/include/CLIc/CL/cl_half.h
itk_clesperanto-0.2.2.data/data/include/CLIc/CL/cl_gl.h
itk_clesperanto-0.2.2.data/data/include/CLIc/CL/opencl.hpp
itk_clesperanto-0.2.2.data/data/include/CLIc/CL/cl.h
itk_clesperanto-0.2.2.data/data/include/CLIc/CL/cl_platform.h
itk_clesperanto-0.2.2.data/data/include/CLIc/CL/cl_d3d11.h
itk_clesperanto-0.2.2.data/data/include/CLIc/CL/cl_dx9_media_sharing.h
itk_clesperanto-0.2.2.data/data/include/CLIc/CL/cl_egl.h
itk_clesperanto-0.2.2.data/data/include/CLIc/CL/cl_layer.h
itk_clesperanto-0.2.2.data/data/include/CLIc/CL/cl2.hpp
itk_clesperanto-0.2.2.data/data/include/CLIc/CL/cl_va_api_media_sharing_intel.h
itk_clesperanto-0.2.2.dist-info/LICENSE
itk_clesperanto-0.2.2.dist-info/top_level.txt
itk_clesperanto-0.2.2.dist-info/WHEEL
itk_clesperanto-0.2.2.dist-info/RECORD
itk_clesperanto-0.2.2.dist-info/METADATA
