Metadata-Version: 2.1
Name: itk-clesperanto
Version: 0.2.2
Summary: ITK filters accelerated with OpenCL.
Home-page: https://itk.org/
Download-URL: https://github.com/InsightSoftwareConsortium/ITKCLEsperanto
Author: NumFOCUS
Author-email: itk+community@discourse.itk.org
License: Apache
Keywords: ITK InsightToolkit
Classifier: License :: OSI Approved :: Apache Software License
Classifier: Programming Language :: Python
Classifier: Programming Language :: C++
Classifier: Development Status :: 4 - Beta
Classifier: Intended Audience :: Developers
Classifier: Intended Audience :: Education
Classifier: Intended Audience :: Healthcare Industry
Classifier: Intended Audience :: Science/Research
Classifier: Topic :: Scientific/Engineering
Classifier: Topic :: Scientific/Engineering :: Medical Science Apps.
Classifier: Topic :: Scientific/Engineering :: Information Analysis
Classifier: Topic :: Software Development :: Libraries
Classifier: Operating System :: Android
Classifier: Operating System :: Microsoft :: Windows
Classifier: Operating System :: POSIX
Classifier: Operating System :: Unix
Classifier: Operating System :: MacOS
License-File: LICENSE
Requires-Dist: itk (>=5.3rc04.post3)
